gym_anytrading/__init__.py
gym_anytrading/datasets/__init__.py
gym_anytrading/datasets/utils.py
gym_anytrading/datasets/data/FOREX_EURUSD_1H_ASK.csv
gym_anytrading/datasets/data/STOCKS_GOOGL.csv
gym_anytrading/envs/__init__.py
gym_anytrading/envs/forex_env.py
gym_anytrading/envs/stocks_env.py
gym_anytrading/envs/trading_env.py
gym_anytrading-2.0.0.dist-info/LICENSE
gym_anytrading-2.0.0.dist-info/METADATA
gym_anytrading-2.0.0.dist-info/WHEEL
gym_anytrading-2.0.0.dist-info/top_level.txt
gym_anytrading-2.0.0.dist-info/RECORD
